pyqt5_tools/__init__.py
pyqt5_tools/_version.py
pyqt5_tools/entrypoints.py
pyqt5_tools/badplugin/__init__.py
pyqt5_tools/badplugin/badwidgetplugin.py
pyqt5_tools/examples/__init__.py
pyqt5_tools/examples/exampleqmlitem.py
pyqt5_tools/examples/exampleqmlitemplugin.py
pyqt5_tools/examples/qmlapp.qml
pyqt5_tools/examples/qmldir
pyqt5_tools/examples/qmltest.qml
pyqt5_tools/tests/__init__.py
pyqt5_tools/tests/test_entrypoints.py
pyqt5_tools-5.15.3.3.2.dist-info/COPYING
pyqt5_tools-5.15.3.3.2.dist-info/METADATA
pyqt5_tools-5.15.3.3.2.dist-info/WHEEL
pyqt5_tools-5.15.3.3.2.dist-info/entry_points.txt
pyqt5_tools-5.15.3.3.2.dist-info/top_level.txt
pyqt5_tools-5.15.3.3.2.dist-info/RECORD
